MANIFEST.in
README.rst
requirements.txt
setup.py
aam/__init__.py
aam/cli.py
aam/config.ini
aam/options.py
aam/utils.py
aam.egg-info/PKG-INFO
aam.egg-info/SOURCES.txt
aam.egg-info/dependency_links.txt
aam.egg-info/entry_points.txt
aam.egg-info/requires.txt
aam.egg-info/top_level.txt
aam/generator/__init__.py
aam/generator/render.py
aam/reader/__init__.py
aam/reader/markdown.py
aam/reader/reader.py
aam/static/style.css
aam/static/yue.css
aam/templates/.DS_Store
aam/templates/douban.html
aam/templates/gtihub.html
aam/templates/home.html
aam/templates/layout.html
aam/templates/page.html
aam/templates/repo.html