Metadata-Version: 1.1
Name: aam
Version: 0.1.3
Summary: a lightweight about me site generator
Home-page: https://github.com/JmPotato/Aam
Author: JmPotato
Author-email: ghzpotato@gmail.com
License: MIT License
Keywords: Aam,about me,site,static,static page,static site,generator
Platform: UNKNOWN
Classifier: Development Status :: 4 - Beta
Classifier: Environment :: Console
Classifier: License :: OSI Approved :: MIT License
Classifier: Operating System :: MacOS
Classifier: Operating System :: POSIX
Classifier: Operating System :: POSIX :: Linux
Classifier: Programming Language :: Python
Classifier: Programming Language :: Python :: 2.7
